Metadata-Version: 2.1
Name: tomspdb
Version: 0.9
Summary: UNKNOWN
Home-page: https://github.com/talwrii/tomspdb
Author: Talwrii
Author-email: talwrii@gmail.com
License: MIT
Keywords: debugger
Platform: UNKNOWN
